setup.py
scripts/throughpy
throughpy/__init__.py
throughpy/throughpy_data.py
throughpy/throughpy_parser.py
throughpy.egg-info/PKG-INFO
throughpy.egg-info/SOURCES.txt
throughpy.egg-info/dependency_links.txt
throughpy.egg-info/top_level.txt