Metadata-Version: 1.0
Name: throughpy
Version: 0.1
Summary: A script to test throughput of the main interface with a formatted output using iperf3.
Home-page: https://github.com/kanazux/throughpy
Author: Silvio AS a.k.a kanazuchi
Author-email: contato@kanazuchi.com
License: BSD2CLAUSE
Keywords: net python iperf3
Platform: UNKNOWN
